torchlanc/__init__.py
torchlanc/torchlanc.py
torchlanc-1.1.1.dist-info/licenses/LICENSE
torchlanc-1.1.1.dist-info/METADATA
torchlanc-1.1.1.dist-info/WHEEL
torchlanc-1.1.1.dist-info/top_level.txt
torchlanc-1.1.1.dist-info/RECORD
