Metadata-Version: 2.4
Name: torchlanc
Version: 1.1.1
Summary: A High-Quality Lanczos Scaler for PyTorch
Home-page: https://github.com/Artificial-Sweetener/TorchLanc
Author: ArtificialSweetener
Author-email: artificialsweetenerai@proton.me
License: GPL-3.0-or-later
Project-URL: Homepage, https://github.com/Artificial-Sweetener/TorchLanc
Project-URL: Issues, https://github.com/Artificial-Sweetener/TorchLanc/issues
Classifier: License :: OSI Approved :: GNU General Public License v3 or later (GPLv3+)
Classifier: Programming Language :: Python :: 3
Classifier: Operating System :: OS Independent
Requires-Python: >=3.8
License-File: LICENSE
Requires-Dist: torch
Provides-Extra: dev
Requires-Dist: pytest; extra == "dev"
Requires-Dist: torchvision; extra == "dev"
Requires-Dist: numpy; extra == "dev"
Requires-Dist: Pillow; extra == "dev"
Requires-Dist: py-cpuinfo; extra == "dev"
Requires-Dist: python-semantic-release; extra == "dev"
Requires-Dist: commitizen; extra == "dev"
Dynamic: license-file
